gemini_cli/__init__.py
gemini_cli/cli.py
piptalk_cli-1.0.1.dist-info/licenses/LICENSE
piptalk_cli-1.0.1.dist-info/METADATA
piptalk_cli-1.0.1.dist-info/WHEEL
piptalk_cli-1.0.1.dist-info/entry_points.txt
piptalk_cli-1.0.1.dist-info/top_level.txt
piptalk_cli-1.0.1.dist-info/RECORD
