Metadata-Version: 2.4
Name: piptalk-cli
Version: 1.0.1
Summary: A command-line interface for interacting with Google's Gemini AI models
Home-page: https://github.com/YOUR_USERNAME/gemini-cli
Author: Kartikeya Ranjan
Author-email: Kartikeya Ranjan <kartikeyaranjan01@gmail.com>
License: ISC
Project-URL: Homepage, https://github.com/YOUR_USERNAME/gemini-cli
Project-URL: Repository, https://github.com/YOUR_USERNAME/gemini-cli
Keywords: gemini,ai,cli,google,generative-ai,chat,command-line
Classifier: Development Status :: 4 - Beta
Classifier: Intended Audience :: Developers
Classifier: License :: OSI Approved :: ISC License (ISCL)
Classifier: Programming Language :: Python :: 3
Classifier: Programming Language :: Python :: 3.8
Classifier: Programming Language :: Python :: 3.9
Classifier: Programming Language :: Python :: 3.10
Classifier: Programming Language :: Python :: 3.11
Classifier: Programming Language :: Python :: 3.12
Requires-Python: >=3.8
License-File: LICENSE
Requires-Dist: google-generativeai>=0.3.0
Requires-Dist: colorama>=0.4.6
Requires-Dist: python-dotenv>=1.0.0
Dynamic: author
Dynamic: home-page
Dynamic: license-file
Dynamic: requires-python
